pw_py_termcolor/__init__.py
pw_py_termcolor/termcolor.py
pw_py_termcolor-1.0.0.dist-info/AUTHORS.txt
pw_py_termcolor-1.0.0.dist-info/COPYING.txt
pw_py_termcolor-1.0.0.dist-info/METADATA
pw_py_termcolor-1.0.0.dist-info/WHEEL
pw_py_termcolor-1.0.0.dist-info/top_level.txt
pw_py_termcolor-1.0.0.dist-info/RECORD
