Metadata-Version: 2.1
Name: pw-py-termcolor
Version: 1.0.0
Summary: coloring functions to ANSI terminals
Home-page: https://gitlab.com/stdmatt-libs/pw_py_termcolor
Author: stdmatt
Author-email: stdmatt@pixelwizards.io
License: GPLv3
Keywords: terminal,ANSI,termcolors
Platform: UNKNOWN
Classifier: Programming Language :: Python
Classifier: Programming Language :: Python :: 3 :: Only
Classifier: Natural Language :: English
